{
  "generator-jhipster": {
    "promptValues": {
      "packageName": "com.clairesapp"
    },
    "jhipsterVersion": "5.8.2",
    "applicationType": "monolith",
    "baseName": "clairesapp",
    "packageName": "com.clairesapp",
    "packageFolder": "com/clairesapp",
    "serverPort": "8080",
    "authenticationType": "session",
    "cacheProvider": "no",
    "websocket": false,
    "databaseType": "sql",
    "devDatabaseType": "h2Memory",
    "prodDatabaseType": "mysql",
    "searchEngine": false,
    "messageBroker": false,
    "serviceDiscoveryType": false,
    "buildTool": "maven",
    "rememberMeKey": "2c03176827b56a37344b0175a42c2ebaf832a731d017330322080529652f8f82b7cfd7626316f024725573ce9a60266aa67e",
    "clientFramework": "angularX",
    "useSass": true,
    "clientPackageManager": "npm",
    "testFrameworks": [],
    "jhiPrefix": "jhi",
    "entitySuffix": "",
    "dtoSuffix": "DTO",
    "otherModules": [],
    "enableTranslation": false
  }
}